LICENSE
README.md
setup.py
zenodo_rest/__init__.py
zenodo_rest/exceptions.py
zenodo_rest/retries.py
zenodo_rest.egg-info/PKG-INFO
zenodo_rest.egg-info/SOURCES.txt
zenodo_rest.egg-info/dependency_links.txt
zenodo_rest.egg-info/entry_points.txt
zenodo_rest.egg-info/requires.txt
zenodo_rest.egg-info/top_level.txt
zenodo_rest/cli/__init__.py
zenodo_rest/cli/cli.py
zenodo_rest/cli/depositions.py
zenodo_rest/depositions/__init__.py
zenodo_rest/depositions/actions.py
zenodo_rest/entities/__init__.py
zenodo_rest/entities/bucket_file.py
zenodo_rest/entities/community.py
zenodo_rest/entities/creator.py
zenodo_rest/entities/date_interval.py
zenodo_rest/entities/deposition.py
zenodo_rest/entities/deposition_file.py
zenodo_rest/entities/doi.py
zenodo_rest/entities/grant.py
zenodo_rest/entities/location.py
zenodo_rest/entities/metadata.py
zenodo_rest/entities/record.py
zenodo_rest/entities/subject.py
zenodo_rest/entities/zenodo_file.py
zenodo_rest/records/__init__.py
zenodo_rest/records/get.py