Metadata-Version: 2.1
Name: zenodo-rest
Version: 0.0.0b11
Summary: ("A python wrapper of Zenodo's REST API", 'for python and the command line.')
Home-page: https://github.com/kykrueger/zenodo-rest-python.git
Author: Kyle Krueger
Author-email: kyle.s.krueger@gmail.com
License: MIT
Platform: UNKNOWN
Classifier: Programming Language :: Python
Classifier: Programming Language :: Python :: 3
Classifier: Programming Language :: Python :: 3.7
Classifier: Programming Language :: Python :: 3.8
Classifier: Programming Language :: Python :: 3.9
Classifier: Programming Language :: Python :: 3.10
License-File: LICENSE
